ext_distributions/Binomialdistribution.py
ext_distributions/Gaussiandistribution.py
ext_distributions/Generaldistribution.py
ext_distributions/__init__.py
ext_distributions-1.1.dist-info/METADATA
ext_distributions-1.1.dist-info/WHEEL
ext_distributions-1.1.dist-info/top_level.txt
ext_distributions-1.1.dist-info/RECORD
