Metadata-Version: 2.1
Name: ext-distributions
Version: 1.1
Summary: Gaussian distributions and Binomial distributions
Home-page: UNKNOWN
Author: ishan
Author-email: ishan2198@hotmail.com
License: UNKNOWN
Platform: UNKNOWN
